setup.cfg
setup.py
toncenter_sdk/TC_Client.py
toncenter_sdk/_init_.py
toncenter_sdk/toncenter.py
toncenter_sdk/V2/_init_.py
toncenter_sdk/V2/accounts.py
toncenter_sdk/V2/blocks.py
toncenter_sdk/V2/transactions.py
toncenter_sdk/V3/_init_.py
toncenter_sdk/V3/default_.py
toncenter_sdk/cfgs/_init_.py
toncenter_sdk/cfgs/dependencies.py
toncenter_sdk/datas/Data.py
toncenter_sdk/datas/Packs.py
toncenter_sdk/datas/Prepare.py
toncenter_sdk/datas/_init_.py
toncenter_sdk/sides/_init_.py
toncenter_sdk/sides/accounts.py
toncenter_sdk/sides/rest_.py
toncenter_sdk/sides/run_methods.py
toncenter_sdk_python.egg-info/PKG-INFO
toncenter_sdk_python.egg-info/SOURCES.txt
toncenter_sdk_python.egg-info/dependency_links.txt
toncenter_sdk_python.egg-info/not-zip-safe
toncenter_sdk_python.egg-info/top_level.txt