Metadata-Version: 2.1
Name: toncenter_sdk_python
Version: 0.5
Summary: TONCENTER SDK FOR PYTHON
Author-email: dev.nevermore696@gmail.com
